Workbook
Name SegmentaciónDeDatos_Linea: #N/A
Name SegmentaciónDeDatos_Vendedor: #N/A

Sheet Profit Bridge
B21: Ganancia Primer Periodo (ProfitP1) | C21: =CUBEVALUE("ThisWorkbookDataModel",Ventas!$S$3,Ventas!$S$4,"ProfitP1") -> 565 | D21: =CUBEMEMBER("ThisWorkbookDataModel","[Measures].[ProfitP1]") -> ProfitP1
B22: Efecto Volumen (QI) | C22: =CUBEVALUE("ThisWorkbookDataModel",Ventas!$S$3,Ventas!$S$4,"QI") -> 49.030809 | D22: =CUBEMEMBER("ThisWorkbookDataModel","[Measures].[QI]") -> QI
B23: Efecto Precio (PI) | C23: =CUBEVALUE("ThisWorkbookDataModel",Ventas!$S$3,Ventas!$S$4,"PI") -> 187.86237 | D23: =CUBEMEMBER("ThisWorkbookDataModel","[Measures].[PI]") -> PI
B24: Efecto Costo (VI) | C24: =CUBEVALUE("ThisWorkbookDataModel",Ventas!$S$3,Ventas!$S$4,"VI") -> -265.84551 | D24: =CUBEMEMBER("ThisWorkbookDataModel","[Measures].[VI]") -> VI
B25: Efecto Mix (MI) | C25: =CUBEVALUE("ThisWorkbookDataModel",Ventas!$S$3,Ventas!$S$4,"MI") -> -18.047666 | D25: =CUBEMEMBER("ThisWorkbookDataModel","[Measures].[MI]") -> MI
B26: Ganancia Segundo Periodo (ProfitP2) | C26: =CUBEVALUE("ThisWorkbookDataModel",Ventas!$S$3,Ventas!$S$4,"ProfitP2") -> 518 | D26: =CUBEMEMBER("ThisWorkbookDataModel","[Measures].[ProfitP2]") -> ProfitP2

Sheet Ventas
B2: Periodo | C2: Linea | D2: Vendedor | E2: Producto | F2: Cantidad | G2: Precio | H2: CostoVar
B3: P1 | C3: LineaA | D3: Vendedor 1 | E3: A | F3: 35 | G3: 5 | H3: 3 | J3: =+Tabla1[[#This Row],[Precio]]-Tabla1[[#This Row],[CostoVar]] -> 2 | K3: =+Tabla1[[#This Row],[Cantidad]]/SUM($F$3:$F$10) -> 0.19444444 | R3: Linea | S3: All
B4: P1 | C4: LineaA | D4: Vendedor 2 | E4: B | F4: 20 | G4: 9 | H4: 7 | J4: =+Tabla1[[#This Row],[Precio]]-Tabla1[[#This Row],[CostoVar]] -> 2 | K4: =+Tabla1[[#This Row],[Cantidad]]/SUM($F$3:$F$10) -> 0.11111111 | R4: Vendedor | S4: All
B5: P1 | C5: LineaB | D5: Vendedor 3 | E5: C | F5: 20 | G5: 8 | H5: 5 | J5: =+Tabla1[[#This Row],[Precio]]-Tabla1[[#This Row],[CostoVar]] -> 3 | K5: =+Tabla1[[#This Row],[Cantidad]]/SUM($F$3:$F$10) -> 0.11111111
B6: P1 | C6: LineaB | D6: Vendedor 4 | E6: D | F6: 35 | G6: 8 | H6: 4 | J6: =+Tabla1[[#This Row],[Precio]]-Tabla1[[#This Row],[CostoVar]] -> 4 | K6: =+Tabla1[[#This Row],[Cantidad]]/SUM($F$3:$F$10) -> 0.19444444
B7: P1 | C7: LineaA | D7: Vendedor 1 | E7: A | F7: 15 | G7: 5 | H7: 3 | J7: =+Tabla1[[#This Row],[Precio]]-Tabla1[[#This Row],[CostoVar]] -> 2 | K7: =+Tabla1[[#This Row],[Cantidad]]/SUM($F$3:$F$10) -> 0.083333333
B8: P1 | C8: LineaA | D8: Vendedor 2 | E8: B | F8: 10 | G8: 9 | H8: 7 | J8: =+Tabla1[[#This Row],[Precio]]-Tabla1[[#This Row],[CostoVar]] -> 2 | K8: =+Tabla1[[#This Row],[Cantidad]]/SUM($F$3:$F$10) -> 0.055555556
B9: P1 | C9: LineaB | D9: Vendedor 3 | E9: C | F9: 35 | G9: 9 | H9: 4 | J9: =+Tabla1[[#This Row],[Precio]]-Tabla1[[#This Row],[CostoVar]] -> 5 | K9: =+Tabla1[[#This Row],[Cantidad]]/SUM($F$3:$F$10) -> 0.19444444
B10: P1 | C10: LineaB | D10: Vendedor 4 | E10: D | F10: 10 | G10: 8 | H10: 5 | J10: =+Tabla1[[#This Row],[Precio]]-Tabla1[[#This Row],[CostoVar]] -> 3 | K10: =+Tabla1[[#This Row],[Cantidad]]/SUM($F$3:$F$10) -> 0.055555556
B11: P2 | C11: LineaA | D11: Vendedor 1 | E11: A | F11: 25 | G11: 10 | H11: 7 | J11: =+Tabla1[[#This Row],[Precio]]-Tabla1[[#This Row],[CostoVar]] -> 3 | K11: =+Tabla1[[#This Row],[Cantidad]]/SUM($F$11:$F$18) -> 0.12690355
B12: P2 | C12: LineaA | D12: Vendedor 2 | E12: B | F12: 25 | G12: 8 | H12: 6 | J12: =+Tabla1[[#This Row],[Precio]]-Tabla1[[#This Row],[CostoVar]] -> 2 | K12: =+Tabla1[[#This Row],[Cantidad]]/SUM($F$11:$F$18) -> 0.12690355
B13: P2 | C13: LineaB | D13: Vendedor 3 | E13: C | F13: 35 | G13: 9 | H13: 7 | J13: =+Tabla1[[#This Row],[Precio]]-Tabla1[[#This Row],[CostoVar]] -> 2 | K13: =+Tabla1[[#This Row],[Cantidad]]/SUM($F$11:$F$18) -> 0.17766497
B14: P2 | C14: LineaB | D14: Vendedor 4 | E14: D | F14: 25 | G14: 7 | H14: 4 | J14: =+Tabla1[[#This Row],[Precio]]-Tabla1[[#This Row],[CostoVar]] -> 3 | K14: =+Tabla1[[#This Row],[Cantidad]]/SUM($F$11:$F$18) -> 0.12690355
B15: P2 | C15: LineaA | D15: Vendedor 1 | E15: A | F15: 10 | G15: 11 | H15: 8 | J15: =+Tabla1[[#This Row],[Precio]]-Tabla1[[#This Row],[CostoVar]] -> 3 | K15: =+Tabla1[[#This Row],[Cantidad]]/SUM($F$11:$F$18) -> 0.050761421
B16: P2 | C16: LineaA | D16: Vendedor 2 | E16: B | F16: 30 | G16: 7 | H16: 6 | J16: =+Tabla1[[#This Row],[Precio]]-Tabla1[[#This Row],[CostoVar]] -> 1 | K16: =+Tabla1[[#This Row],[Cantidad]]/SUM($F$11:$F$18) -> 0.15228426
B17: P2 | C17: LineaB | D17: Vendedor 3 | E17: C | F17: 35 | G17: 10 | H17: 6 | J17: =+Tabla1[[#This Row],[Precio]]-Tabla1[[#This Row],[CostoVar]] -> 4 | K17: =+Tabla1[[#This Row],[Cantidad]]/SUM($F$11:$F$18) -> 0.17766497
B18: P2 | C18: LineaB | D18: Vendedor 4 | E18: D | F18: 12 | G18: 8 | H18: 4 | J18: =+Tabla1[[#This Row],[Precio]]-Tabla1[[#This Row],[CostoVar]] -> 4 | K18: =+Tabla1[[#This Row],[Cantidad]]/SUM($F$11:$F$18) -> 0.060913706
